{"version":3,"kind":"Article","sha256":"0131cb37c6ad2d936a37caa90693e706d5b11cb397040838532220bbecff4943","slug":"interacting-with-jupyter-books","location":"/shared_files_finpy/Interacting With Jupyter Books.md","dependencies":[],"frontmatter":{"title":"🪐 Working with Jupyter Books","content_includes_title":false,"authors":[{"nameParsed":{"literal":"Financial Python","given":"Financial","family":"Python"},"name":"Financial Python","id":"contributors-myst-generated-uid-0"}],"github":"https://github.com/PatrickJHess/Volume-Four-Chapter-Three","copyright":"2025 by the University of Virginia Darden School Foundation, Charlottesville, VA.","numbering":{"title":{"offset":1}},"source_url":"https://github.com/PatrickJHess/Volume-Four-Chapter-Three/blob/main/shared_files_finpy/Interacting With Jupyter Books.md","edit_url":"https://github.com/PatrickJHess/Volume-Four-Chapter-Three/edit/main/shared_files_finpy/Interacting With Jupyter Books.md","exports":[{"format":"md","filename":"Interacting With Jupyter Books.md","url":"/Volume-Four-Chapter-Three//build/Interacting With Jup-f927471c80a4b95773908fd6a41063df.md"}]},"mdast":{"type":"root","children":[{"type":"block","children":[{"type":"paragraph","position":{"start":{"line":3,"column":1},"end":{"line":3,"column":1}},"children":[{"type":"text","value":"Two types of documents are utilized across this and other chapters to deliver content and code:","position":{"start":{"line":3,"column":1},"end":{"line":3,"column":1}},"key":"RnQsjcN2BK"}],"key":"T6cheWE4qJ"},{"type":"heading","depth":3,"position":{"start":{"line":5,"column":1},"end":{"line":5,"column":1}},"children":[{"type":"strong","position":{"start":{"line":5,"column":1},"end":{"line":5,"column":1}},"children":[{"type":"text","value":"📄 1. Markdown Documents (.md)","position":{"start":{"line":5,"column":1},"end":{"line":5,"column":1}},"key":"EOVJzEKyOI"}],"key":"WjPB7VsmUF"}],"identifier":"id-1-markdown-documents-md","label":"📄 1. Markdown Documents (.md)","html_id":"id-1-markdown-documents-md","implicit":true,"key":"QS3L7waNIE"},{"type":"list","ordered":false,"spread":false,"position":{"start":{"line":7,"column":1},"end":{"line":10,"column":1}},"children":[{"type":"listItem","spread":true,"position":{"start":{"line":7,"column":1},"end":{"line":7,"column":1}},"children":[{"type":"paragraph","children":[{"type":"strong","position":{"start":{"line":7,"column":1},"end":{"line":7,"column":1}},"children":[{"type":"text","value":"What it is:","position":{"start":{"line":7,"column":1},"end":{"line":7,"column":1}},"key":"yzjd2mbzKk"}],"key":"BEhNHmtXKT"},{"type":"text","value":" Static text (like what you are currently reading).","position":{"start":{"line":7,"column":1},"end":{"line":7,"column":1}},"key":"sqc9TSQuv9"}],"key":"r8OZ9NtIWs"}],"key":"wFPcJANbdB"},{"type":"listItem","spread":true,"position":{"start":{"line":8,"column":1},"end":{"line":8,"column":1}},"children":[{"type":"paragraph","children":[{"type":"strong","position":{"start":{"line":8,"column":1},"end":{"line":8,"column":1}},"children":[{"type":"text","value":"Code:","position":{"start":{"line":8,"column":1},"end":{"line":8,"column":1}},"key":"AEl3c3Lo94"}],"key":"x1TXiyOAMV"},{"type":"text","value":" Contains no executable code.","position":{"start":{"line":8,"column":1},"end":{"line":8,"column":1}},"key":"iTlU009dZE"}],"key":"orgDKghdyH"}],"key":"hYCIty0S0H"},{"type":"listItem","spread":true,"position":{"start":{"line":9,"column":1},"end":{"line":10,"column":1}},"children":[{"type":"paragraph","children":[{"type":"strong","position":{"start":{"line":9,"column":1},"end":{"line":9,"column":1}},"children":[{"type":"text","value":"Downloads:","position":{"start":{"line":9,"column":1},"end":{"line":9,"column":1}},"key":"evxaGw5tIS"}],"key":"S4DuStK32j"},{"type":"text","value":" Available to save as a Markdown (.md) or PDF (.pdf) file.","position":{"start":{"line":9,"column":1},"end":{"line":9,"column":1}},"key":"wuN92qL74E"}],"key":"x5FSDxiapE"}],"key":"SJHbYtiWce"}],"key":"b9JFAeuo9v"},{"type":"heading","depth":3,"position":{"start":{"line":11,"column":1},"end":{"line":11,"column":1}},"children":[{"type":"strong","position":{"start":{"line":11,"column":1},"end":{"line":11,"column":1}},"children":[{"type":"text","value":"🧑‍💻 2. Notebook Documents (.ipynb)","position":{"start":{"line":11,"column":1},"end":{"line":11,"column":1}},"key":"G7kqlBX6Fy"}],"key":"kFIk0E7nTp"}],"identifier":"id-2-notebook-documents-ipynb","label":"🧑‍💻 2. Notebook Documents (.ipynb)","html_id":"id-2-notebook-documents-ipynb","implicit":true,"key":"EUprliwAg1"},{"type":"list","ordered":false,"spread":false,"position":{"start":{"line":13,"column":1},"end":{"line":16,"column":1}},"children":[{"type":"listItem","spread":true,"position":{"start":{"line":13,"column":1},"end":{"line":13,"column":1}},"children":[{"type":"paragraph","children":[{"type":"strong","position":{"start":{"line":13,"column":1},"end":{"line":13,"column":1}},"children":[{"type":"text","value":"What it is:","position":{"start":{"line":13,"column":1},"end":{"line":13,"column":1}},"key":"zVw2pZ62ut"}],"key":"GAMiEagRkN"},{"type":"text","value":" HTML representations of interactive Jupyter Notebooks.","position":{"start":{"line":13,"column":1},"end":{"line":13,"column":1}},"key":"SNq4El6OeM"}],"key":"FqSVEBsQgE"}],"key":"PXAHSGHpWZ"},{"type":"listItem","spread":true,"position":{"start":{"line":14,"column":1},"end":{"line":14,"column":1}},"children":[{"type":"paragraph","children":[{"type":"strong","position":{"start":{"line":14,"column":1},"end":{"line":14,"column":1}},"children":[{"type":"text","value":"Code:","position":{"start":{"line":14,"column":1},"end":{"line":14,"column":1}},"key":"fo8W3PcYUs"}],"key":"BqQ3OySfgW"},{"type":"text","value":" Fully interactive. You can run code inside the HTML file or via Binder using Jupyter Lab.","position":{"start":{"line":14,"column":1},"end":{"line":14,"column":1}},"key":"wM6gV255p9"}],"key":"fHnnPD287C"}],"key":"CUmVotkqTm"},{"type":"listItem","spread":true,"position":{"start":{"line":15,"column":1},"end":{"line":16,"column":1}},"children":[{"type":"paragraph","children":[{"type":"strong","position":{"start":{"line":15,"column":1},"end":{"line":15,"column":1}},"children":[{"type":"text","value":"Downloads:","position":{"start":{"line":15,"column":1},"end":{"line":15,"column":1}},"key":"Wwikbj9DAN"}],"key":"kuagjKSdlB"},{"type":"text","value":" Available to save as a Notebook (.ipynb) or PDF (.pdf) file.","position":{"start":{"line":15,"column":1},"end":{"line":15,"column":1}},"key":"ZDCH2Yota0"}],"key":"HWzbfqN1gG"}],"key":"qRetoHfn04"}],"key":"qyBHja367h"},{"type":"heading","depth":2,"position":{"start":{"line":17,"column":1},"end":{"line":17,"column":1}},"children":[{"type":"strong","position":{"start":{"line":17,"column":1},"end":{"line":17,"column":1}},"children":[{"type":"text","value":"🚀 Notebook Launch Options","position":{"start":{"line":17,"column":1},"end":{"line":17,"column":1}},"key":"MXbxRBAoef"}],"key":"QXxoX3kgmA"}],"identifier":"id-notebook-launch-options","label":"🚀 Notebook Launch Options","html_id":"id-notebook-launch-options","implicit":true,"key":"sllEAMxV32"},{"type":"paragraph","position":{"start":{"line":19,"column":1},"end":{"line":19,"column":1}},"children":[{"type":"text","value":"For .ipynb files, you have three ways to interact with the code:","position":{"start":{"line":19,"column":1},"end":{"line":19,"column":1}},"key":"lQDDTmsxxJ"}],"key":"EPE1SjlX1f"},{"type":"table","position":{"start":{"line":21,"column":1},"end":{"line":25,"column":1}},"children":[{"type":"tableRow","position":{"start":{"line":21,"column":1},"end":{"line":21,"column":1}},"children":[{"type":"tableCell","header":true,"align":"left","position":{"start":{"line":21,"column":1},"end":{"line":21,"column":1}},"children":[{"type":"text","value":"Option","position":{"start":{"line":21,"column":1},"end":{"line":21,"column":1}},"key":"Hdxem1siDn"}],"key":"ZgmvFp9O5T"},{"type":"tableCell","header":true,"align":"left","position":{"start":{"line":21,"column":1},"end":{"line":21,"column":1}},"children":[{"type":"text","value":"Description","position":{"start":{"line":21,"column":1},"end":{"line":21,"column":1}},"key":"tI9kFYKcJb"}],"key":"piu6xG4GYS"},{"type":"tableCell","header":true,"align":"left","position":{"start":{"line":21,"column":1},"end":{"line":21,"column":1}},"children":[{"type":"text","value":"Interactive Features","position":{"start":{"line":21,"column":1},"end":{"line":21,"column":1}},"key":"kYJGWFHRWc"}],"key":"n50x1D2EWb"},{"type":"tableCell","header":true,"align":"left","position":{"start":{"line":21,"column":1},"end":{"line":21,"column":1}},"children":[{"type":"text","value":"Keep in Mind","position":{"start":{"line":21,"column":1},"end":{"line":21,"column":1}},"key":"fBD45XP4wx"}],"key":"RiHM9ZI72I"}],"key":"oTyzsWdME8"},{"type":"tableRow","position":{"start":{"line":23,"column":1},"end":{"line":23,"column":1}},"children":[{"type":"tableCell","align":"left","position":{"start":{"line":23,"column":1},"end":{"line":23,"column":1}},"children":[{"type":"text","value":"📦 ","position":{"start":{"line":23,"column":1},"end":{"line":23,"column":1}},"key":"fU06iIzK38"},{"type":"strong","position":{"start":{"line":23,"column":1},"end":{"line":23,"column":1}},"children":[{"type":"text","value":"Binder","position":{"start":{"line":23,"column":1},"end":{"line":23,"column":1}},"key":"grTpoJPZXd"}],"key":"pDZGeitDc3"}],"key":"rBEB6xi0gR"},{"type":"tableCell","align":"left","position":{"start":{"line":23,"column":1},"end":{"line":23,"column":1}},"children":[{"type":"text","value":"Launches remotely in a new tab.","position":{"start":{"line":23,"column":1},"end":{"line":23,"column":1}},"key":"cBjDtAwq9X"}],"key":"mziRBtCrCJ"},{"type":"tableCell","align":"left","position":{"start":{"line":23,"column":1},"end":{"line":23,"column":1}},"children":[{"type":"text","value":"Execute, add, modify, and download.","position":{"start":{"line":23,"column":1},"end":{"line":23,"column":1}},"key":"IHZ7c3asiw"}],"key":"qotwRBTN8m"},{"type":"tableCell","align":"left","position":{"start":{"line":23,"column":1},"end":{"line":23,"column":1}},"children":[{"type":"text","value":"Changes are not saved after closing (ephemeral container).","position":{"start":{"line":23,"column":1},"end":{"line":23,"column":1}},"key":"UwsHYKDGpc"}],"key":"R8TKrBJCIS"}],"key":"GC7K8Zh8FI"},{"type":"tableRow","position":{"start":{"line":24,"column":1},"end":{"line":24,"column":1}},"children":[{"type":"tableCell","align":"left","position":{"start":{"line":24,"column":1},"end":{"line":24,"column":1}},"children":[{"type":"text","value":"☁️ ","position":{"start":{"line":24,"column":1},"end":{"line":24,"column":1}},"key":"RIchywMiK6"},{"type":"strong","position":{"start":{"line":24,"column":1},"end":{"line":24,"column":1}},"children":[{"type":"text","value":"Colab","position":{"start":{"line":24,"column":1},"end":{"line":24,"column":1}},"key":"hDlzwau89D"}],"key":"lq3fzbeMhs"}],"key":"LjO3xWqeJ2"},{"type":"tableCell","align":"left","position":{"start":{"line":24,"column":1},"end":{"line":24,"column":1}},"children":[{"type":"text","value":"Fast access via Google’s cloud.","position":{"start":{"line":24,"column":1},"end":{"line":24,"column":1}},"key":"U4jlpa87L6"}],"key":"XIlgOzU4Q6"},{"type":"tableCell","align":"left","position":{"start":{"line":24,"column":1},"end":{"line":24,"column":1}},"children":[{"type":"text","value":"Execute cells or save a copy.","position":{"start":{"line":24,"column":1},"end":{"line":24,"column":1}},"key":"f0khK4i4dk"}],"key":"IbaRhV1jNw"},{"type":"tableCell","align":"left","position":{"start":{"line":24,"column":1},"end":{"line":24,"column":1}},"children":[{"type":"text","value":"Requires a Google login to run or copy.","position":{"start":{"line":24,"column":1},"end":{"line":24,"column":1}},"key":"vrRBnMUGYf"}],"key":"VCCPKBsvrk"}],"key":"Umi3gvqkdl"},{"type":"tableRow","position":{"start":{"line":25,"column":1},"end":{"line":25,"column":1}},"children":[{"type":"tableCell","align":"left","position":{"start":{"line":25,"column":1},"end":{"line":25,"column":1}},"children":[{"type":"text","value":"⚡ ","position":{"start":{"line":25,"column":1},"end":{"line":25,"column":1}},"key":"Rdajk5TZGC"},{"type":"strong","position":{"start":{"line":25,"column":1},"end":{"line":25,"column":1}},"children":[{"type":"text","value":"Live Code","position":{"start":{"line":25,"column":1},"end":{"line":25,"column":1}},"key":"fNhSULImIr"}],"key":"zJjil47tp3"}],"key":"CoOG94zYSx"},{"type":"tableCell","align":"left","position":{"start":{"line":25,"column":1},"end":{"line":25,"column":1}},"children":[{"type":"text","value":"Runs directly on the page via Binder.","position":{"start":{"line":25,"column":1},"end":{"line":25,"column":1}},"key":"SLbt7JGe1t"}],"key":"viESAXyiWn"},{"type":"tableCell","align":"left","position":{"start":{"line":25,"column":1},"end":{"line":25,"column":1}},"children":[{"type":"text","value":"Execute existing code.","position":{"start":{"line":25,"column":1},"end":{"line":25,"column":1}},"key":"BU3vjI0hf7"}],"key":"TkjpadmIqX"},{"type":"tableCell","align":"left","position":{"start":{"line":25,"column":1},"end":{"line":25,"column":1}},"children":[{"type":"text","value":"Cannot add, modify, or save cells.","position":{"start":{"line":25,"column":1},"end":{"line":25,"column":1}},"key":"KTYXgWGQu1"}],"key":"QPBHUkSx1K"}],"key":"O6vzcT3n1E"}],"key":"PqxNmY12la"},{"type":"heading","depth":2,"position":{"start":{"line":27,"column":1},"end":{"line":27,"column":1}},"children":[{"type":"strong","position":{"start":{"line":27,"column":1},"end":{"line":27,"column":1}},"children":[{"type":"text","value":"🎛️ Additional Interactive Features","position":{"start":{"line":27,"column":1},"end":{"line":27,"column":1}},"key":"ywc14EY0nD"}],"key":"Pb1r09QSuo"}],"identifier":"id-additional-interactive-features","label":"🎛️ Additional Interactive Features","html_id":"id-additional-interactive-features","implicit":true,"key":"UaHGPEM6Bw"},{"type":"list","ordered":false,"spread":false,"position":{"start":{"line":29,"column":1},"end":{"line":32,"column":1}},"children":[{"type":"listItem","spread":true,"position":{"start":{"line":29,"column":1},"end":{"line":29,"column":1}},"children":[{"type":"paragraph","children":[{"type":"text","value":"⏯️ ","position":{"start":{"line":29,"column":1},"end":{"line":29,"column":1}},"key":"SL9Pkap8Hj"},{"type":"strong","position":{"start":{"line":29,"column":1},"end":{"line":29,"column":1}},"children":[{"type":"text","value":"Run Live Code:","position":{"start":{"line":29,"column":1},"end":{"line":29,"column":1}},"key":"rGM6eauL0e"}],"key":"LrUzPRD1Ev"},{"type":"text","value":" Click the ","position":{"start":{"line":29,"column":1},"end":{"line":29,"column":1}},"key":"ldtwDiU6sV"},{"type":"strong","position":{"start":{"line":29,"column":1},"end":{"line":29,"column":1}},"children":[{"type":"text","value":"start button","position":{"start":{"line":29,"column":1},"end":{"line":29,"column":1}},"key":"rd31ss0kof"}],"key":"oxp9OdGyTR"},{"type":"text","value":" at the top of a notebook page to execute code directly inside the HTML file.","position":{"start":{"line":29,"column":1},"end":{"line":29,"column":1}},"key":"yOSjZiiz3W"}],"key":"ZUHFOiDplv"}],"key":"UEnklpPaui"},{"type":"listItem","spread":true,"position":{"start":{"line":30,"column":1},"end":{"line":30,"column":1}},"children":[{"type":"paragraph","children":[{"type":"text","value":"🛸 ","position":{"start":{"line":30,"column":1},"end":{"line":30,"column":1}},"key":"P569tJQpjZ"},{"type":"strong","position":{"start":{"line":30,"column":1},"end":{"line":30,"column":1}},"children":[{"type":"text","value":"Quick Launch:","position":{"start":{"line":30,"column":1},"end":{"line":30,"column":1}},"key":"U4onM8dMbe"}],"key":"eq71zij3W2"},{"type":"text","value":" The first cell in every notebook includes direct links to open the environment in ","position":{"start":{"line":30,"column":1},"end":{"line":30,"column":1}},"key":"lgXhu1KT7V"},{"type":"strong","position":{"start":{"line":30,"column":1},"end":{"line":30,"column":1}},"children":[{"type":"text","value":"Colab","position":{"start":{"line":30,"column":1},"end":{"line":30,"column":1}},"key":"Y9QU9yj5N5"}],"key":"jDDZh3Fatr"},{"type":"text","value":" or ","position":{"start":{"line":30,"column":1},"end":{"line":30,"column":1}},"key":"p8DJcOMZk8"},{"type":"strong","position":{"start":{"line":30,"column":1},"end":{"line":30,"column":1}},"children":[{"type":"text","value":"Binder","position":{"start":{"line":30,"column":1},"end":{"line":30,"column":1}},"key":"S9pkCEJRPs"}],"key":"x9cGh5Hpj0"},{"type":"text","value":".","position":{"start":{"line":30,"column":1},"end":{"line":30,"column":1}},"key":"UflFxOiirv"}],"key":"T1bh99dZP9"}],"key":"d4E27GtNLv"},{"type":"listItem","spread":true,"position":{"start":{"line":31,"column":1},"end":{"line":32,"column":1}},"children":[{"type":"paragraph","children":[{"type":"text","value":"📋 ","position":{"start":{"line":31,"column":1},"end":{"line":31,"column":1}},"key":"lcCHcD81E7"},{"type":"strong","position":{"start":{"line":31,"column":1},"end":{"line":31,"column":1}},"children":[{"type":"text","value":"One-Click Copy:","position":{"start":{"line":31,"column":1},"end":{"line":31,"column":1}},"key":"tf6crSpPDG"}],"key":"DoLgsuqSy5"},{"type":"text","value":" Hover over the upper-right corner of any code cell or block to quickly copy the script to your clipboard.","position":{"start":{"line":31,"column":1},"end":{"line":31,"column":1}},"key":"GsxkzbVZT2"}],"key":"jeLwVaYXaW"}],"key":"euRDGza99h"}],"key":"nHKwOw5vC9"},{"type":"heading","depth":2,"position":{"start":{"line":33,"column":1},"end":{"line":33,"column":1}},"children":[{"type":"strong","position":{"start":{"line":33,"column":1},"end":{"line":33,"column":1}},"children":[{"type":"text","value":"🎯 Summary","position":{"start":{"line":33,"column":1},"end":{"line":33,"column":1}},"key":"GxLpJqooRy"}],"key":"ivxZzAtYgT"}],"identifier":"id-summary","label":"🎯 Summary","html_id":"id-summary","implicit":true,"key":"AGHYJTrvV1"},{"type":"paragraph","position":{"start":{"line":35,"column":1},"end":{"line":35,"column":1}},"children":[{"type":"text","value":"By combining narrative Markdown with interactive Notebooks, Jupyter Books seamlessly bridge the gap between financial theory and real-world applications.","position":{"start":{"line":35,"column":1},"end":{"line":35,"column":1}},"key":"l8uBiTqDZD"}],"key":"U5creB61A9"}],"key":"zXGRnudcfs"}],"key":"Uxtgx1QCFX"},"references":{"cite":{"order":[],"data":{}}},"footer":{"navigation":{"prev":{"title":"\"📈🛠️ Yields To Maturity and The Term Structure: Theory & Practice\"","url":"/","group":"\"📈🛠️ Yields To Maturity and The Term Structure: Theory & Practice\""},"next":{"title":"✨ Chapter Highlights","short_title":"✨ Chapter Highlights","url":"/chapter-three-highlights","group":"Chapter Three: Yields To Maturity And The Term Structure Of Interest Rates"}}},"domain":"http://localhost:3000"}